README.md
setup.py
codegenhelper/__init__.py
codegenhelper/debug.py
codegenhelper/env.py
codegenhelper/githelper.py
codegenhelper/log.py
codegenhelper.egg-info/PKG-INFO
codegenhelper.egg-info/SOURCES.txt
codegenhelper.egg-info/dependency_links.txt
codegenhelper.egg-info/top_level.txt